design.sv
//Name: Haiyi Zhang
//Assignment:Zhang Final Project
//Purpose:Implement the traffic signal controller
//Module Names:Signals

module dff (clk,set, reset,d, q, qn); // D-Flip Flop
  input      clk,set,reset,d; //declare inputs clk, reset and d
  output     q,qn;        //declare outputs q and qn
  reg        q;           //declare q is reg
  assign qn = ~q;		  //assign qn equal not q

  always @(posedge clk or posedge reset)
  begin
    if (reset) begin  // asynchronous reset when reset goes high
      
      q <= 0;    //non-blocking
    end else begin    // assign D to Q on positive clock edge
      
      q <= d;    //non-blcking
    end
  end
endmodule

module Signals(clk,S,SH,SC,set,reset);
  input clk, S,set,reset; // declare input clk, S, set and reset
  output reg SH, SC;      // declare output reg SH and SC
  

  reg Q1, Q0;  //declare reg Q1 and Q0

  
  wire D1,D0,nS,nQ1,nQ0;  //create wires for gates
  not #1(nS,S);    // NOT gate for S
  not #1(nQ1, Q1); // NOT gate for Q1
  not #1(nQ0,Q0);  // NOT gate for Q0
  
  and #2(D1,nQ0,nS);  // and gate for nQ0 and nS
  and #2(D0,nQ1,S);   // and gate for nQ1 and S



  wire nSH,nSC,n1,n2;  //Create wires
  dff t1(.clk(clk),.d(D1),.q(Q1),.qn(nQ1),.set(set),.reset(reset)); //Q1<=D1
  //instantiate clk with clk, d with D1, q with Q1, qn with nQ1, set with set, reset with reset
  dff t2(.clk(clk),.d(D0),.q(Q0),.qn(nQ0),.set(set),.reset(reset)); //Q0<=D0
  //instantiate clk with clk, d with D0, q with Q0, qn with nQ0, set with set, reset with reset
  dff t3(.clk(clk),.d(Q1),.q(SH),.qn(nSH),.set(set),.reset(reset)); //SH<=Q1
  //instantiate clk with clk, d with Q1, q with SH, qn with nSH, set with set, reset with reset
  dff t4(.clk(clk),.d(Q0),.q(SC),.qn(nSC),.set(set),.reset(reset)); //SC<=Q0
  //instantiate clk with clk, d with Q0, q with SC, qn with nSC, set with set, reset with reset
  
endmodule

testbench.sv
//Name: Haiyi Zhang
//Assignment:Zhang Final Project
//Purpose:Test Implement of the traffic signal controller
//Module Names:Signals_tb


module Signals_tb;
  wire SH,SC;  // declare outputs SH and SC for test
  reg clk, S,set,reset; // declare inputs clk,S,set and reset for test

  
  initial
    begin
      S=0;clk=0;reset=0; //Q1=1 Q0=0 SH=1 SC=0
    end
  
  always
    #1 clk=!clk; // A clock Signal

  
   always  //code for all the test cases
    begin
      
      #20 S=1;reset=0; //Q1=1 Q0=0 SH=0 SC=1
      #20 S=1;reset=0; //Q1=0 Q0=1 SH=0 SC=1
      #20 S=0;reset=0; //Q1=0 Q0=1 SH=1 SC=0
      
      #20 S=0;reset=1; //Q1=1 Q0=0 SH=0 SC=0
      #20 S=0;reset=0; //Q1=0 Q0=0 SH=0 SC=1
      
      #20 S=0;reset=1; //Q1=0 Q0=1 SH=0 SC=0
      #20 S=1;reset=0; //Q1=0 Q1=0 SH=0 SC=1
      
      #20 S=1;reset=1; //Q1=0 Q0=1 SH=0 SH=0
      #20 S=0;reset=1; //Q1=0 Q0=0 SH=0 SH=0
      #20 S=1;reset=1; //Q1=0 Q0=0 SH=0 SH=0
      
      #20 S=0;reset=0; //Q1=0 Q0=0 SH=1 SH=0
      #20 S=1;reset=1; //Q1=1 Q0=0 SH=0 SH=0
      
      
      


      
    end
  
  Signals t(.clk(clk),.S(S),.SH(SH),.SC(SC),.set(set),.reset(reset));
  //instantiate clk with clk, S with S, SH with SH, SC with SC, set with set, reset with reset
  initial
    begin // Create EPWave
      $dumpfile("test.vcd");
      $dumpvars;
    end
  
  initial
    begin
      $display("S\tSH\tSC"); // code for header row
      $monitor("%d\t%d\t%d",S,SH,SC);  //code for monitor
    end
  
  
  initial //run time
    #260 $finish;

    
endmodule

test.vcd
$date
	Sat Aug  7 22:42:52 2021
$end
$version
	Icarus Verilog
$end
$timescale
	1s
$end
$scope module Signals_tb $end
$var wire 1 ! SH $end
$var wire 1 " SC $end
$var reg 1 # S $end
$var reg 1 $ clk $end
$var reg 1 % reset $end
$var reg 1 & set $end
$scope module t $end
$var wire 1 ' D0 $end
$var wire 1 ( D1 $end
$var wire 1 # S $end
$var wire 1 $ clk $end
$var wire 1 ) nQ0 $end
$var wire 1 * nQ1 $end
$var wire 1 + nS $end
$var wire 1 % reset $end
$var wire 1 & set $end
$var wire 1 , nSH $end
$var wire 1 - nSC $end
$var wire 1 ! SH $end
$var wire 1 " SC $end
$var wire 1 . Q1 $end
$var wire 1 / Q0 $end
$scope module t1 $end
$var wire 1 $ clk $end
$var wire 1 ( d $end
$var wire 1 * qn $end
$var wire 1 % reset $end
$var wire 1 & set $end
$var reg 1 . q $end
$upscope $end
$scope module t2 $end
$var wire 1 $ clk $end
$var wire 1 ' d $end
$var wire 1 ) qn $end
$var wire 1 % reset $end
$var wire 1 & set $end
$var reg 1 / q $end
$upscope $end
$scope module t3 $end
$var wire 1 $ clk $end
$var wire 1 . d $end
$var wire 1 , qn $end
$var wire 1 % reset $end
$var wire 1 & set $end
$var reg 1 ! q $end
$upscope $end
$scope module t4 $end
$var wire 1 $ clk $end
$var wire 1 / d $end
$var wire 1 - qn $end
$var wire 1 % reset $end
$var wire 1 & set $end
$var reg 1 " q $end
$upscope $end
$upscope $end
$upscope $end
$enddefinitions $end
#0
$dumpvars
x/
x.
x-
x,
x+
x*
x)
x(
x'
x&
0%
0$
0#
x"
x!
$end
#1
1+
1$
#2
0$
0'
#3
0/
1$
#4
1)
0$
#5
1-
0"
1$
#6
0$
1(
#7
1.
1$
#8
0*
0$
#9
0,
1!
1$
#10
0$
#11
1$
#12
0$
#13
1$
#14
0$
#15
1$
#16
0$
#17
1$
#18
0$
#19
1$
#20
0$
1#
#21
0+
1$
#22
0$
#23
x*
0.
1$
0(
#24
1*
0$
#25
1,
0!
1$
#26
0$
1'
#27
x)
1/
1$
#28
0)
0$
#29
0-
1"
1$
#30
0$
#31
1$
#32
0$
#33
1$
#34
0$
#35
1$
#36
0$
#37
1$
#38
0$
#39
1$
#40
0$
#41
1$
#42
0$
#43
1$
#44
0$
#45
1$
#46
0$
#47
1$
#48
0$
#49
1$
#50
0$
#51
1$
#52
0$
#53
1$
#54
0$
#55
1$
#56
0$
#57
1$
#58
0$
#59
1$
#60
0$
0#
#61
1+
1$
#62
0$
0'
#63
x)
0/
1$
#64
1)
0$
#65
1-
0"
1$
#66
0$
1(
#67
x*
1.
1$
#68
0*
0$
#69
0,
1!
1$
#70
0$
#71
1$
#72
0$
#73
1$
#74
0$
#75
1$
#76
0$
#77
1$
#78
0$
#79
1$
#80
x*
1,
0.
0!
0$
1%
#81
1*
1$
#82
0$
#83
1$
#84
0$
#85
1$
#86
0$
#87
1$
#88
0$
#89
1$
#90
0$
#91
1$
#92
0$
#93
1$
#94
0$
#95
1$
#96
0$
#97
1$
#98
0$
#99
1$
#100
0$
0%
#101
x*
1.
1$
#102
0*
0$
#103
0,
1!
1$
#104
0$
#105
1$
#106
0$
#107
1$
#108
0$
#109
1$
#110
0$
#111
1$
#112
0$
#113
1$
#114
0$
#115
1$
#116
0$
#117
1$
#118
0$
#119
1$
#120
1,
x*
0!
0.
0$
1%
#121
1*
1$
#122
0$
#123
1$
#124
0$
#125
1$
#126
0$
#127
1$
#128
0$
#129
1$
#130
0$
#131
1$
#132
0$
#133
1$
#134
0$
#135
1$
#136
0$
#137
1$
#138
0$
#139
1$
#140
0$
0%
1#
#141
x*
1.
0+
1$
#142
0*
0$
#143
0,
x*
1!
0.
1$
0(
#144
1*
0$
#145
1,
0!
1$
#146
0$
1'
#147
x)
1/
1$
#148
0)
0$
#149
0-
1"
1$
#150
0$
#151
1$
#152
0$
#153
1$
#154
0$
#155
1$
#156
0$
#157
1$
#158
0$
#159
1$
#160
x)
1-
0/
0"
0$
1%
#161
1)
1$
#162
0$
#163
1$
#164
0$
#165
1$
#166
0$
#167
1$
#168
0$
#169
1$
#170
0$
#171
1$
#172
0$
#173
1$
#174
0$
#175
1$
#176
0$
#177
1$
#178
0$
#179
1$
#180
0$
0#
#181
1+
1$
#182
0$
0'
#183
1$
1(
#184
0$
#185
1$
#186
0$
#187
1$
#188
0$
#189
1$
#190
0$
#191
1$
#192
0$
#193
1$
#194
0$
#195
1$
#196
0$
#197
1$
#198
0$
#199
1$
#200
0$
1#
#201
0+
1$
#202
0$
1'
#203
1$
0(
#204
0$
#205
1$
#206
0$
#207
1$
#208
0$
#209
1$
#210
0$
#211
1$
#212
0$
#213
1$
#214
0$
#215
1$
#216
0$
#217
1$
#218
0$
#219
1$
#220
0$
0%
0#
#221
x)
1/
1+
1$
#222
0)
0$
0'
#223
x)
0-
0/
1"
1$
#224
1)
0$
#225
1-
0"
1$
#226
0$
1(
#227
x*
1.
1$
#228
0*
0$
#229
0,
1!
1$
#230
0$
#231
1$
#232
0$
#233
1$
#234
0$
#235
1$
#236
0$
#237
1$
#238
0$
#239
1$
#240
1,
x*
0!
0.
0$
1%
1#
#241
1*
0+
1$
#242
0$
#243
1$
1'
0(
#244
0$
#245
1$
#246
0$
#247
1$
#248
0$
#249
1$
#250
0$
#251
1$
#252
0$
#253
1$
#254
0$
#255
1$
#256
0$
#257
1$
#258
0$
#259
1$
#260
0$
0%
